CMakeLists.txt
MANIFEST.in
README.md
README_PYTHON.txt
VERSION
setup.py
extern/Catch2/CMakeLists.txt
extern/Catch2/LICENSE.txt
extern/Catch2/CMake/Catch2Config.cmake.in
extern/Catch2/CMake/FindGcov.cmake
extern/Catch2/CMake/FindLcov.cmake
extern/Catch2/CMake/Findcodecov.cmake
extern/Catch2/CMake/MiscFunctions.cmake
extern/Catch2/CMake/catch2.pc.in
extern/Catch2/CMake/llvm-cov-wrapper
extern/Catch2/contrib/Catch.cmake
extern/Catch2/contrib/CatchAddTests.cmake
extern/Catch2/contrib/ParseAndAddCatchTests.cmake
extern/Catch2/contrib/gdbinit
extern/Catch2/contrib/lldbinit
extern/Catch2/include/catch.hpp
extern/Catch2/include/catch_with_main.hpp
extern/Catch2/include/external/clara.hpp
extern/Catch2/include/internal/catch_approx.cpp
extern/Catch2/include/internal/catch_approx.h
extern/Catch2/include/internal/catch_assertionhandler.cpp
extern/Catch2/include/internal/catch_assertionhandler.h
extern/Catch2/include/internal/catch_assertioninfo.h
extern/Catch2/include/internal/catch_assertionresult.cpp
extern/Catch2/include/internal/catch_assertionresult.h
extern/Catch2/include/internal/catch_capture.hpp
extern/Catch2/include/internal/catch_capture_matchers.cpp
extern/Catch2/include/internal/catch_capture_matchers.h
extern/Catch2/include/internal/catch_clara.h
extern/Catch2/include/internal/catch_commandline.cpp
extern/Catch2/include/internal/catch_commandline.h
extern/Catch2/include/internal/catch_common.cpp
extern/Catch2/include/internal/catch_common.h
extern/Catch2/include/internal/catch_compiler_capabilities.h
extern/Catch2/include/internal/catch_config.cpp
extern/Catch2/include/internal/catch_config.hpp
extern/Catch2/include/internal/catch_console_colour.cpp
extern/Catch2/include/internal/catch_console_colour.h
extern/Catch2/include/internal/catch_context.cpp
extern/Catch2/include/internal/catch_context.h
extern/Catch2/include/internal/catch_debug_console.cpp
extern/Catch2/include/internal/catch_debug_console.h
extern/Catch2/include/internal/catch_debugger.cpp
patchdistances.egg-info/PKG-INFO
patchdistances.egg-info/SOURCES.txt
patchdistances.egg-info/dependency_links.txt
patchdistances.egg-info/not-zip-safe
patchdistances.egg-info/top_level.txt
