Metadata-Version: 1.0
Name: patchdistances
Version: 1.0
Summary: Invariant patch distances and clustering
Home-page: https://gitlab.com/a.schulze/patch_assignment_filter
Author: Andre Schulze
Author-email: a.schulze@stud.un-heidelberg.de
License: MIT
Platform: UNKNOWN
